mmrwrapper/__init__.py
mmrwrapper/exceptions.py
mmrwrapper/wrapper.py
mmrwrapper-0.0.8.dist-info/LICENSE.txt
mmrwrapper-0.0.8.dist-info/METADATA
mmrwrapper-0.0.8.dist-info/WHEEL
mmrwrapper-0.0.8.dist-info/top_level.txt
mmrwrapper-0.0.8.dist-info/RECORD
