Metadata-Version: 2.1
Name: mmrwrapper
Version: 0.0.8
Summary: API-Wrapper WhatIsMyMMR
Home-page: UNKNOWN
Author: Sunta
Author-email: noneofyour@business.com
License: UNKNOWN
Keywords: python,api,wrapper
Platform: UNKNOWN
Classifier: Intended Audience :: Developers
Classifier: Programming Language :: Python :: 3
Classifier: Operating System :: Microsoft :: Windows
Requires-Dist: asyncio
Requires-Dist: aiohttp
